[
//Buildings
	{
		"name": "Grove",
		"cost": 150,
		"maintenance": 0,
		"hurryCostModifier": 25,
		"replacementTextForUniques": "Unimproved tiles in this city receive +1 Food, +1 Faith"
		"uniques": ["[+1 Food, +1 Faith] from [All] tiles [in this city] <in [unimproved] [All] tiles>"],
		"requiredTech": "Calendar"
	},
	{
		"name": "Gunsmith Shop",
		"cost": 160,
		"maintenance": 1,
		"hurryCostModifier": 25,
		"uniques": ["[+15]% Production when constructing [Gunpowder] units [in this city]", "[+15]% Production when constructing [Ranged Gunpowder] units [in this city]"],
		"requiredTech": "Gunpowder"
	},
	{
		"name": "Chocolate House",
		"requiredNearbyImprovedResources": ["Bananas", "Citrus", "Cocoa", "Cotton", "Dyes", "Incense", "Silk", "Spices", "Sugar", "Wine"],
		"cost": 100,
		"hurryCostModifier": 25,
		"uniques": ["[+1 Gold] from [Plantation] tiles [in this city]", "[+2 Gold] from [Cocoa] tiles [in this city]"]
		"requiredTech": "Navigation"
	},
	{
		"name": "Sewer System",
		"cost": 200,
		"maintenance": 2,
		"hurryCostModifier": 25,
		"uniques": ["[+15]% growth [in this city]", "[-10]% Unhappiness from [Population] [in this city]"],
		"requiredTech": "Industrialization"
	},
	{
		"name": "Aquarium",
		"happiness": 3,
		"cost": 360,
		"maintenance": 2,
		"hurryCostModifier": 25,
		"uniques": ["Must be next to [Coast]", "[+2 Science] from [Water resource] tiles [in this city]", "[+2 Science] from [Atoll] tiles [in this city]"],
		"requiredTech": "Biology"
	},
	{
		"name": "Supermarket",
		"food": 4,
		"cost": 385,
		"maintenance": 3,
		"hurryCostModifier": 25,
		"uniques": ["[+1 Food] from [Cattle] tiles [in this city]", "[+1 Food] from [Deer] tiles [in this city]", "[+1 Food] from [Wheat] tiles [in this city]", "[+1 Food] from [Plantation] tiles [in this city]"],
		"requiredTech": "Replaceable Parts"
	},
	{
		"name": "Laser Defense",
		"cityStrength": 15,
		"cityHealth": 50,
		"hurryCostModifier": 25,
		"requiredBuilding": "Military Base",
		"uniques": ["Destroyed when the city is captured"],
		"requiredTech": "Lasers"
	},

//Wonders

	{
		"name": "Transmigration Bureau",
		"cost": 215,
		"maintenance": 2,
		"isNationalWonder": true,
		"uniques": ["Can only be built [in capital]", "[-2] population [in this city]", "[+50]% Production when constructing [Settler] units [in this city]", "[2] free [Settler] units appear", "Cost increases by [50] per owned city"],
		"requiredTech": "Navigation"
	},
	{
		"name": "Red Cross",
		"cost": 600,
		"isNationalWonder": true,
		"uniques": ["Requires a [Hospital] in all cities", "All newly-trained [relevant] units [in this city] receive the [Medic] promotion", "Cost increases by [30] per owned city"],
		"requiredTech": "Pharmaceuticals"
	},

//Support for modded civs (New Vegas is the first to be added here because yes I am just a teensy tiny bit of a Fallout simp)

	{
		"name": "King's School of Impersonation",
		"replaces": "Opera House",
		"uniqueTo": "New Vegas",
		"culture": 4,
		"specialistSlots": {"Artist": 1},
		"requiredBuilding": "Amphitheater",
		"maintenance": 2,
		"hurryCostModifier": 0,
		"uniques": ["[+1 Culture] per [2] population [in this city]", "Destroyed when the city is captured"],
		"requiredTech": "Acoustics"
	},
	{
		"name": "Old Mormon Fort",
		"replaces": "Walls",
		"uniqueTo": "New Vegas",
		"science": 2,
		"cost": 65,
		"cityStrength": 5,
		"cityHealth": 50,
		"hurryCostModifier": 25,
		"uniques": ["Destroyed when the city is captured", "[All] adjacent units to this city heal [10] HP when healing"],
		"requiredTech": "Masonry"
	},
	{
		"name": "Silver Rush",
		"replaces": "Gunsmith Shop",
		"uniqueTo": "New Vegas",
		"gold": 2,
		"cost": 160,
		"maintenance": 0,
		"hurryCostModifier": 0,
		"uniques": ["[+15]% Production when constructing [Gunpowder] units [in this city]", "[+15]% Production when constructing [Ranged Gunpowder] units [in this city]"],
		"requiredTech": "Gunpowder"
	},
]
